opytimizer/__init__.py
opytimizer/opytimizer.py
opytimizer/core/__init__.py
opytimizer/core/agent.py
opytimizer/core/block.py
opytimizer/core/cell.py
opytimizer/core/function.py
opytimizer/core/node.py
opytimizer/core/optimizer.py
opytimizer/core/space.py
opytimizer/functions/__init__.py
opytimizer/functions/constrained.py
opytimizer/functions/multi_objective/__init__.py
opytimizer/functions/multi_objective/standard.py
opytimizer/functions/multi_objective/weighted.py
opytimizer/math/__init__.py
opytimizer/math/distribution.py
opytimizer/math/general.py
opytimizer/math/hyper.py
opytimizer/math/random.py
opytimizer/optimizers/__init__.py
opytimizer/optimizers/boolean/__init__.py
opytimizer/optimizers/boolean/bmrfo.py
opytimizer/optimizers/boolean/bpso.py
opytimizer/optimizers/boolean/umda.py
opytimizer/optimizers/evolutionary/__init__.py
opytimizer/optimizers/evolutionary/bsa.py
opytimizer/optimizers/evolutionary/de.py
opytimizer/optimizers/evolutionary/ep.py
opytimizer/optimizers/evolutionary/es.py
opytimizer/optimizers/evolutionary/foa.py
opytimizer/optimizers/evolutionary/ga.py
opytimizer/optimizers/evolutionary/gp.py
opytimizer/optimizers/evolutionary/gsgp.py
opytimizer/optimizers/evolutionary/hs.py
opytimizer/optimizers/evolutionary/iwo.py
opytimizer/optimizers/evolutionary/rra.py
opytimizer/optimizers/misc/__init__.py
opytimizer/optimizers/misc/aoa.py
opytimizer/optimizers/misc/cem.py
opytimizer/optimizers/misc/doa.py
opytimizer/optimizers/misc/gs.py
opytimizer/optimizers/misc/hc.py
opytimizer/optimizers/misc/nds.py
opytimizer/optimizers/population/__init__.py
opytimizer/optimizers/population/aeo.py
opytimizer/optimizers/population/ao.py
opytimizer/optimizers/population/coa.py
opytimizer/optimizers/population/epo.py
opytimizer/optimizers/population/gco.py
opytimizer/optimizers/population/gwo.py
opytimizer/optimizers/population/hho.py
opytimizer/optimizers/population/loa.py
opytimizer/optimizers/population/osa.py
opytimizer/optimizers/population/ppa.py
opytimizer-3.1.4.dist-info/LICENSE
opytimizer-3.1.4.dist-info/METADATA
opytimizer-3.1.4.dist-info/WHEEL
opytimizer-3.1.4.dist-info/top_level.txt
opytimizer-3.1.4.dist-info/RECORD
