Metadata-Version: 2.1
Name: opytimizer
Version: 3.1.4
Summary: Nature-Inspired Python Optimizer
Home-page: https://github.com/gugarosa/opytimizer
Author: Gustavo Rosa
Author-email: gustavo.rosa@unesp.br
License: Apache 2.0
Classifier: Development Status :: 5 - Production/Stable
Classifier: Intended Audience :: Developers
Classifier: Intended Audience :: Education
Classifier: Intended Audience :: Science/Research
Classifier: License :: OSI Approved :: Apache Software License
Classifier: Programming Language :: Python :: 3.6
Classifier: Programming Language :: Python :: 3.7
Classifier: Programming Language :: Python :: 3.8
Classifier: Programming Language :: Python :: 3.9
Classifier: Topic :: Software Development :: Libraries
Classifier: Topic :: Software Development :: Libraries :: Python Modules
License-File: LICENSE
Requires-Dist: coverage >=5.5
Requires-Dist: dill >=0.3.4
Requires-Dist: matplotlib >=3.3.4
Requires-Dist: networkx >=2.5.1
Requires-Dist: numpy >=1.19.5
Requires-Dist: opytimark >=1.0.7
Requires-Dist: pre-commit >=2.17.0
Requires-Dist: pylint >=2.7.2
Requires-Dist: pytest >=6.2.2
Requires-Dist: tqdm >=4.49.0
Provides-Extra: tests
Requires-Dist: coverage ; extra == 'tests'
Requires-Dist: pytest ; extra == 'tests'
Requires-Dist: pytest-pep8 ; extra == 'tests'
